klampt/version.py
klampt/__init__.py
klampt/_robotsim.cpython-312-darwin.so
klampt/robotsim.py
klampt/plan/rigidobjectcspace.py
klampt/plan/robotplanning.py
klampt/plan/cspace.py
klampt/plan/robotcspace.py
klampt/plan/__init__.py
klampt/plan/cspaceutils.py
klampt/plan/robotoptimize.py
klampt/plan/contactcspace.py
klampt/plan/motionplanning.py
klampt/plan/_motionplanning.cpython-312-darwin.so
klampt/plan/kinetrajopt/trajopt_task_space.py
klampt/plan/kinetrajopt/__init__.py
klampt/plan/kinetrajopt/kinetrajopt.py
klampt/plan/kinetrajopt/utils.py
klampt/io/numpy_convert.py
klampt/io/trimesh_convert.py
klampt/io/html.py
klampt/io/resource.py
klampt/io/__init__.py
klampt/io/loader.py
klampt/io/rerun_convert.py
klampt/io/open3d_convert.py
klampt/io/povray_animation.py
klampt/io/ros.py
klampt/io/povray.py
klampt/math/optimize.py
klampt/math/symbolic_klampt.py
klampt/math/rootfind.py
klampt/math/geodesic.py
klampt/math/spline.py
klampt/math/se3.py
klampt/math/_rootfind.cpython-312-darwin.so
klampt/math/vectorfield.py
klampt/math/__init__.py
klampt/math/vectorops.py
klampt/math/symbolic.py
klampt/math/symbolic_linalg.py
klampt/math/symbolic_io.py
klampt/math/so3.py
klampt/math/so2.py
klampt/math/symbolic_sympy.py
klampt/math/autodiff/dynamics_ad.py
klampt/math/autodiff/so3_ad.py
klampt/math/autodiff/se3_ad.py
klampt/math/autodiff/trajectory_ad.py
klampt/math/autodiff/kinematics_ad.py
klampt/math/autodiff/__init__.py
klampt/math/autodiff/pytorch.py
klampt/math/autodiff/ad.py
klampt/math/autodiff/geometry_ad.py
klampt/math/autodiff/math_ad.py
klampt/.dylibs/libassimp.5.4.3.dylib
klampt/vis/editors.py
klampt/vis/glrobotprogram.py
klampt/vis/glinterface.py
klampt/vis/__init__.py
klampt/vis/visualization.py
klampt/vis/camera.py
klampt/vis/glcommon.py
klampt/vis/glinit.py
klampt/vis/colorize.py
klampt/vis/glprogram.py
klampt/vis/gldraw.py
klampt/vis/glviewport.py
klampt/vis/ipython/_version.py
klampt-0.10.1.dist-info/RECORD
klampt-0.10.1.dist-info/WHEEL
klampt-0.10.1.dist-info/entry_points.txt
klampt-0.10.1.dist-info/top_level.txt
klampt-0.10.1.dist-info/METADATA
